{
	"ships": [
		{ "id":1, "name":"LEE A.TREGURTHA", "cargo":500, "capacity":1000, "port":null },
		{ "id":2, "name":"MAERSK MC KINNEY MOLLER", "cargo":500, "capacity":1000, "port":null },
		{ "id":3, "name":"EDWIN H.GOTT", "cargo":500, "capacity":1000, "port":null },
		{ "id":4, "name":"PAUL R.TREGURTHA", "cargo":500, "capacity":1000, "port":null },
		{ "id":5, "name":"EBBA MAERSK", "cargo":500, "capacity":1000, "port":null },
		{ "id":6, "name":"MAJESTIC MAERSK", "cargo":500, "capacity":1000, "port":null },
		{ "id":7, "name":"BLUE MARLIN", "cargo":500, "capacity":1000, "port":null },
		{ "id":8, "name":"CMA CGM MARCO POLO", "cargo":500, "capacity":1000, "port":null },
		{ "id":9, "name":"JAMES R.BARKER", "cargo":500, "capacity":1000, "port":null },
		{ "id":10, "name":"CSCL GLOBE", "cargo":500, "capacity":1000, "port":null },
		{ "id":11, "name":"EDITH MAERSK", "cargo":500, "capacity":1000, "port":null },
		{ "id":12, "name":"ARTHUR M.ANDERSON", "cargo":500, "capacity":1000, "port":null },
		{ "id":13, "name":"MSC OSCAR", "cargo":500, "capacity":1000, "port":null },
		{ "id":14, "name":"STEWART J.CORT", "cargo":500, "capacity":1000, "port":null },
		{ "id":15, "name":"OOCL HONG KONG", "cargo":500, "capacity":1000, "port":null },
		{ "id":16, "name":"MARY MAERSK", "cargo":500, "capacity":1000, "port":null },
		{ "id":17, "name":"CASON J.CALLAWAY", "cargo":500, "capacity":1000, "port":null },
		{ "id":18, "name":"ROGER BLOUGH", "cargo":500, "capacity":1000, "port":null },
		{ "id":19, "name":"EUGEN MAERSK", "cargo":500, "capacity":1000, "port":null },
		{ "id":20, "name":"BOKA VANGUARD", "cargo":500, "capacity":1000, "port":null },
		{ "id":21, "name":"ALPENA", "cargo":500, "capacity":1000, "port":null },
		{ "id":22, "name":"MESABI MINER", "cargo":500, "capacity":1000, "port":null },
		{ "id":23, "name":"ELEONORA MAERSK", "cargo":500, "capacity":1000, "port":null },
		{ "id":24, "name":"CMA CGM JULES VERNE", "cargo":500, "capacity":1000, "port":null }
	]
}